{
  "cli": {
    "version": ">= 13.0.0",
    "appVersionSource": "remote"
  },
  "build": {
    "development": {
      "developmentClient": true,
      "distribution": "internal",
      "channel": "dev",
      "android": {
        "buildType": "apk"
      },
      "env": {
        "EXPO_PUBLIC_API_URL": "http://10.0.2.2:4000/api/v1"
      }
    },
    "preview": {
      "distribution": "internal",
      "channel": "staging",
      "android": {
        "buildType": "apk"
      },
      "env": {
        "EXPO_PUBLIC_API_URL": "https://staging-api.badhiya.store/api/v1"
      }
    },
    "production": {
      "channel": "production",
      "autoIncrement": true,
      "env": {
        "EXPO_PUBLIC_API_URL": "https://api.badhiya.store/api/v1",
        "EXPO_PUBLIC_ENVIRONMENT": "production"
      }
    }
  },
  "submit": {
    "production": {
      "android": {
        "serviceAccountKeyPath": "./service-account.json",
        "track": "production",
        "releaseStatus": "draft"
      }
    }
  }
}
